{
    "robot": {
        "kind": 2,
        "x": 1,
        "y": 2
    },
    "field": {
        "sx": 10,
        "sy": 4,
        "cells": [
            [" ", " ", " ", " ", " ", " ", " ", " ", " ", " "],
            [" ", " ", " ", " ", " ", " ", " ", " ", " ", " "],
            [" ", " ", " ", "b", " ", " ", "b", " ", " ", " "],
            [" ", " ", " ", " ", " ", " ", " ", " ", " ", " "]
        ],
        "vfences": [
            "         ",
            "  || ||  ",
            "        |",
            "         "
        ],
        "hfences": [
            "   -  -   ",
            "  - -- -- ",
            "  ------- "
        ]
    }
}
